nonogram/__init__.py
nonogram/main.py
nonogram/res/default_values.json
nonogram/res/entry_points_documentation.xml
nonogram/res/global_variables.json
nonogram/res/parameters_documentation.json
nonogram/res/parameters_names.json
nonogram/src/__init__.py
nonogram/src/core/__init__.py
nonogram/src/core/nonogram.py
nonogram/src/core/grille/__init__.py
nonogram/src/core/grille/affichage.py
nonogram/src/core/grille/grille_utils.py
nonogram/src/core/grille/parser.py
nonogram/src/core/solveurs/__init__.py
nonogram/src/core/solveurs/dynamic_optimized_programming.py
nonogram/src/core/solveurs/dynamic_programming.py
nonogram/src/core/solveurs/linear_programming.py
nonogram/src/core/solveurs/solveur_utils.py
nonogram/src/getters/__init__.py
nonogram/src/getters/environment.py
nonogram/src/getters/get_default_value.py
nonogram/src/getters/get_entry_point_documentation.py
nonogram/src/getters/get_global_variable.py
nonogram/src/getters/get_parameter_documentation.py
nonogram/src/getters/get_parameter_name.py
nonogram/src/initialization/__init__.py
nonogram/src/initialization/args_cleaner.py
nonogram/src/initialization/args_parser.py
nonogram-3.1.1.dist-info/LICENSE.txt
nonogram-3.1.1.dist-info/METADATA
nonogram-3.1.1.dist-info/WHEEL
nonogram-3.1.1.dist-info/entry_points.txt
nonogram-3.1.1.dist-info/top_level.txt
nonogram-3.1.1.dist-info/RECORD
